azurestapi.py
azurestapi-0.0.1.dist-info/LICENSE.txt
azurestapi-0.0.1.dist-info/METADATA
azurestapi-0.0.1.dist-info/WHEEL
azurestapi-0.0.1.dist-info/top_level.txt
azurestapi-0.0.1.dist-info/RECORD
