Metadata-Version: 2.1
Name: azurestapi
Version: 0.0.1
Summary: A Python Package to List Azure Resources for Different Azure Services!
Home-page: https://github.com/akashjeez/azurestapi
Author: akashjeez
Author-email: akashit63@gmail.com
License: UNKNOWN
Platform: UNKNOWN
Classifier: Programming Language :: Python :: 3
Classifier: License :: OSI Approved :: MIT License
Classifier: Operating System :: OS Independent
Requires-Python: >=3.8
Requires-Dist: requests
Requires-Dist: pandas
Requires-Dist: xlsxwriter
